csim/CodeSimilarity.py
csim/Visitors.py
csim/__init__.py
csim/main.py
csim/utils.py
csim/python/PythonLexer.py
csim/python/PythonLexerBase.py
csim/python/PythonParser.py
csim/python/PythonParserVisitor.py
csim/python/__init__.py
csim/python/utils.py
csim-1.4.1.dist-info/licenses/LICENSE
csim-1.4.1.dist-info/METADATA
csim-1.4.1.dist-info/WHEEL
csim-1.4.1.dist-info/entry_points.txt
csim-1.4.1.dist-info/top_level.txt
csim-1.4.1.dist-info/RECORD
