Metadata-Version: 2.4
Name: csim
Version: 1.4.1
Summary: Code Similarity (csim) is a method designed to detect similarity between source codes
Home-page: https://github.com/EdsonEddy/csim
Author: Eddy Lecoña
Author-email: crew0eddy@gmail.com
License: MIT
Project-URL: Bug Tracker, https://github.com/EdsonEddy/csim/issues
Project-URL: Documentation, https://github.com/EdsonEddy/csim/wiki
Project-URL: Source Code, https://github.com/EdsonEddy/csim
Keywords: code analysis,similarity detection,tree parser,tree edit distance,code snippets,code comparison
Platform: All
Classifier: Programming Language :: Python :: 3
Classifier: License :: OSI Approved :: MIT License
Classifier: Operating System :: OS Independent
Classifier: Development Status :: 4 - Beta
Requires-Python: >=3.9
License-File: LICENSE
Requires-Dist: antlr4-python3-runtime
Requires-Dist: zss
Dynamic: author
Dynamic: author-email
Dynamic: classifier
Dynamic: description
Dynamic: description-content-type
Dynamic: home-page
Dynamic: keywords
Dynamic: license
Dynamic: license-file
Dynamic: platform
Dynamic: project-url
Dynamic: requires-dist
Dynamic: requires-python
Dynamic: summary
